odoo10_addon_cms_delete_content-10.0.1.0.2-py2.7-nspkg.pth
odoo/addons/cms_delete_content/CHANGES.rst
odoo/addons/cms_delete_content/README.rst
odoo/addons/cms_delete_content/__init__.py
odoo/addons/cms_delete_content/__manifest__.py
odoo/addons/cms_delete_content/controllers/__init__.py
odoo/addons/cms_delete_content/controllers/main.py
odoo/addons/cms_delete_content/i18n/de.po
odoo/addons/cms_delete_content/models/__init__.py
odoo/addons/cms_delete_content/models/test_models.py
odoo/addons/cms_delete_content/models/website_published.py
odoo/addons/cms_delete_content/static/description/icon.png
odoo/addons/cms_delete_content/static/src/js/delete_content.js
odoo/addons/cms_delete_content/templates/assets.xml
odoo/addons/cms_delete_content/templates/delete_confirm.xml
odoo/addons/cms_delete_content/tests/__init__.py
odoo/addons/cms_delete_content/tests/fake_models.py
odoo/addons/cms_delete_content/tests/test_delete.py
odoo10_addon_cms_delete_content-10.0.1.0.2.dist-info/DESCRIPTION.rst
odoo10_addon_cms_delete_content-10.0.1.0.2.dist-info/METADATA
odoo10_addon_cms_delete_content-10.0.1.0.2.dist-info/RECORD
odoo10_addon_cms_delete_content-10.0.1.0.2.dist-info/WHEEL
odoo10_addon_cms_delete_content-10.0.1.0.2.dist-info/metadata.json
odoo10_addon_cms_delete_content-10.0.1.0.2.dist-info/namespace_packages.txt
odoo10_addon_cms_delete_content-10.0.1.0.2.dist-info/top_level.txt
